HellFlask/__init__.py
HellFlask/create.py
HellFlask/delete.py
HellFlask/run.py
HellFlask-0.0.3.dist-info/LICENSE
HellFlask-0.0.3.dist-info/METADATA
HellFlask-0.0.3.dist-info/WHEEL
HellFlask-0.0.3.dist-info/top_level.txt
HellFlask-0.0.3.dist-info/RECORD
