Metadata-Version: 2.1
Name: HellFlask
Version: 0.0.3
Summary: Automate the creation of flask websites.
Home-page: https://github.com/freazesss/hell
Author: freazesss
Author-email: freazesss@gmail.com
License: MIT
Platform: UNKNOWN
